restQL/__init__.py
restQL/client.py
restQL-0.1.2.dist-info/DESCRIPTION.rst
restQL-0.1.2.dist-info/METADATA
restQL-0.1.2.dist-info/RECORD
restQL-0.1.2.dist-info/WHEEL
restQL-0.1.2.dist-info/metadata.json
restQL-0.1.2.dist-info/top_level.txt
